multidim_indexing/__init__.py
multidim_indexing/numpy_view.py
multidim_indexing/torch_view.py
multidim_indexing/view.py
multidim_indexing-1.0.1.dist-info/LICENSE.txt
multidim_indexing-1.0.1.dist-info/METADATA
multidim_indexing-1.0.1.dist-info/WHEEL
multidim_indexing-1.0.1.dist-info/top_level.txt
multidim_indexing-1.0.1.dist-info/RECORD
