Metadata-Version: 2.1
Name: multidim_indexing
Version: 1.0.1
Summary: Multidimensional batch indexing of pytorch tensors and numpy arrays
Author-email: Sheng Zhong <zhsh@umich.edu>
Maintainer-email: Sheng Zhong <zhsh@umich.edu>
License: Copyright (c) 2023 Sheng Zhong
Project-URL: Homepage, https://github.com/LemonPi/multidim_indexing
Project-URL: Bug Reports, https://github.com/LemonPi/multidim_indexing/issues
Project-URL: Source, https://github.com/LemonPi/multidim_indexing
Keywords: numpy,pytorch,indexing
Classifier: Development Status :: 4 - Beta
Classifier: Intended Audience :: Developers
Classifier: License :: OSI Approved :: MIT License
Classifier: Programming Language :: Python :: 3
Classifier: Programming Language :: Python :: 3 :: Only
Requires-Python: >=3.6
License-File: LICENSE.txt
Provides-Extra: all
Requires-Dist: torch ; extra == 'all'
Requires-Dist: numpy ; extra == 'all'
Provides-Extra: numpy
Requires-Dist: numpy ; extra == 'numpy'
Provides-Extra: test
Requires-Dist: pytest ; extra == 'test'
Provides-Extra: torch
Requires-Dist: torch ; extra == 'torch'
